MANIFEST.in
README.rst
setup.py
pyresto/__init__.py
pyresto/core.py
pyresto.egg-info/PKG-INFO
pyresto.egg-info/SOURCES.txt
pyresto.egg-info/dependency_links.txt
pyresto.egg-info/top_level.txt
pyresto/apis/__init__.py
pyresto/apis/bugzilla/__init__.py
pyresto/apis/bugzilla/models.py
pyresto/apis/github/__init__.py
pyresto/apis/github/models.py