Metadata-Version: 1.1
Name: pyresto
Version: 0.3
Summary: A general REST based ORM.
Home-page: https://github.com/BYK/pyresto
Author: Burak Yiğit Kaya
Author-email: ben@byk.im
License: Mozilla Public License, v. 2.0
Platform: UNKNOWN
Classifier: Development Status :: 4 - Beta
Classifier: Environment :: Web Environment
Classifier: License :: OSI Approved :: Mozilla Public License 2.0 (MPL 2.0)
Classifier: Operating System :: OS Independent
Classifier: Natural Language :: English
Classifier: Intended Audience :: Developers
Classifier: Programming Language :: Python
Classifier: Programming Language :: Python :: 2.6
Classifier: Programming Language :: Python :: 2.7
Classifier: Topic :: Software Development :: Libraries
